fine_python_package_info/__init__.py
fine_python_package_info/group_project_files_by_lang_python.py
fine_python_package_info/list_project_files_by_lang_python.py
fine_python_package_info/py_package_layout_info_provider.py
fine_python_package_info-0.2.0a1.dist-info/METADATA
fine_python_package_info-0.2.0a1.dist-info/WHEEL
fine_python_package_info-0.2.0a1.dist-info/top_level.txt
fine_python_package_info-0.2.0a1.dist-info/RECORD
