Metadata-Version: 2.4
Name: fine_python_package_info
Version: 0.2.0a1
Author-email: Vladyslav Hnatiuk <aders1234@gmail.com>
Requires-Python: <=3.14,>=3.11
Requires-Dist: finecode_extension_api==0.4.*
Requires-Dist: tomlkit==0.11.*
